pybrood/__init__.py
pybrood/abc.py
pybrood/inner.pyd
pybrood-0.9.2.dist-info/DESCRIPTION.rst
pybrood-0.9.2.dist-info/METADATA
pybrood-0.9.2.dist-info/RECORD
pybrood-0.9.2.dist-info/WHEEL
pybrood-0.9.2.dist-info/metadata.json
pybrood-0.9.2.dist-info/top_level.txt
