Metadata-Version: 2.0
Name: pybrood
Version: 0.9.2
Summary: Broodwar API binding
Home-page: https://github.com/neumond/pybrood
Author: Vitalik Verhovodov
Author-email: knifeslaughter@gmail.com
License: MIT
Keywords: bwapi starcraft broodwar ai binding
Platform: UNKNOWN
Classifier: Development Status :: 4 - Beta
Classifier: Intended Audience :: Education
Classifier: License :: OSI Approved :: MIT License
Classifier: Programming Language :: Python :: 3.5
Classifier: Programming Language :: Python :: 3.6
Classifier: Topic :: Games/Entertainment
Classifier: Operating System :: Microsoft :: Windows
Classifier: Operating System :: Microsoft :: Windows :: Windows 7
